Metadata-Version: 1.1
Name: qc3
Version: 0.2
Summary: QuickCheck: randomized testing made trivial. Forked to make it work with Python 3.
Home-page: https://github.com/PawelTroka/qc3
Author: Peter Scott, Pawel Troka
Author-email: peter@greplin.com, pawel.troka@outlook.com
License: Apache
Keywords: qc
Platform: UNKNOWN
Classifier: Development Status :: 5 - Production/Stable
Classifier: Intended Audience :: Developers
Classifier: Topic :: Software Development :: Testing
Classifier: License :: OSI Approved :: Apache Software License
Classifier: Programming Language :: Python :: 3
Classifier: Programming Language :: Python :: 3.2
Classifier: Programming Language :: Python :: 3.3
Classifier: Programming Language :: Python :: 3.4
Classifier: Programming Language :: Python :: 3.5
Classifier: Programming Language :: Python :: 3.6
Classifier: Programming Language :: Python :: 3.7
